open_nsfw_python3/LICENSE.md
open_nsfw_python3/README.md
open_nsfw_python3/__init__.py
open_nsfw_python3/deploy.prototxt
open_nsfw_python3/resnet_50_1by2_nsfw.caffemodel
open_nsfw_python3-0.0.5.dist-info/LICENSE.md
open_nsfw_python3-0.0.5.dist-info/METADATA
open_nsfw_python3-0.0.5.dist-info/WHEEL
open_nsfw_python3-0.0.5.dist-info/top_level.txt
open_nsfw_python3-0.0.5.dist-info/RECORD
