Metadata-Version: 2.1
Name: open-nsfw-python3
Version: 0.0.5
Summary: A useful package to detect sexual content based on yahoo's open_nsfw.
Home-page: https://github.com/ds-oliveira/open_nsfw_python3
Author: Danilo Silva de Oliveira
Author-email: danilooliveira28@hotmail.com
License: UNKNOWN
Platform: UNKNOWN
Classifier: Programming Language :: Python :: 3
Classifier: Operating System :: OS Independent
Classifier: Topic :: Scientific/Engineering :: Image Recognition
Requires-Python: >=3.6
Requires-Dist: numpy (>=1.16.4)
Requires-Dist: image (>=1.5.27)
